vercheck/__init__.py
vercheck/about.py
vercheck/py.typed
vercheck/vercheck.py
vercheck-0.2.0.dist-info/LICENSE
vercheck-0.2.0.dist-info/METADATA
vercheck-0.2.0.dist-info/WHEEL
vercheck-0.2.0.dist-info/entry_points.txt
vercheck-0.2.0.dist-info/top_level.txt
vercheck-0.2.0.dist-info/RECORD
