Metadata-Version: 2.1
Name: vercheck
Version: 0.2.0
Summary: Check if a version number is PEP-440 compliant and optionally compare it against a version specified in a python file or the PKG-INFO metadata file.
Author-email: Christian Ledermann <christian.ledermann@gmail.com>
License: MIT
Project-URL: Homepage, https://github.com/cleder/vercheck/
Keywords: __version__,cli,introspection
Classifier: Development Status :: 3 - Alpha
Classifier: Environment :: Console
Classifier: Intended Audience :: Developers
Classifier: License :: OSI Approved :: MIT License
Classifier: Operating System :: OS Independent
Classifier: Programming Language :: Python
Classifier: Programming Language :: Python :: 3.10
Classifier: Programming Language :: Python :: 3.11
Classifier: Programming Language :: Python :: 3.12
Classifier: Programming Language :: Python :: 3.13
Classifier: Typing :: Typed
Requires-Python: >=3.10
License-File: LICENSE
Provides-Extra: complexity
Requires-Dist: lizard ; extra == 'complexity'
Requires-Dist: radon ; extra == 'complexity'
Provides-Extra: dev
Requires-Dist: pre-commit ; extra == 'dev'
Requires-Dist: vercheck[complexity] ; extra == 'dev'
Requires-Dist: vercheck[linting] ; extra == 'dev'
Requires-Dist: vercheck[tests] ; extra == 'dev'
Requires-Dist: vercheck[typing] ; extra == 'dev'
Provides-Extra: linting
Requires-Dist: black ; extra == 'linting'
Requires-Dist: flake8 ; extra == 'linting'
Requires-Dist: flake8-cognitive-complexity ; extra == 'linting'
Requires-Dist: flake8-comments ; extra == 'linting'
Requires-Dist: flake8-complex-f-strings ; extra == 'linting'
Requires-Dist: flake8-continuation ; extra == 'linting'
Requires-Dist: flake8-docstrings ; extra == 'linting'
Requires-Dist: flake8-encodings ; extra == 'linting'
Requires-Dist: flake8-expression-complexity ; extra == 'linting'
Requires-Dist: flake8-function-order ; extra == 'linting'
Requires-Dist: flake8-pep3101 ; extra == 'linting'
Requires-Dist: flake8-super ; extra == 'linting'
Requires-Dist: flake8-use-fstring ; extra == 'linting'
Requires-Dist: ruff ; extra == 'linting'
Requires-Dist: yamllint ; extra == 'linting'
Provides-Extra: tests
Requires-Dist: hypothesis ; extra == 'tests'
Requires-Dist: pytest ; extra == 'tests'
Requires-Dist: pytest-cov ; extra == 'tests'
Provides-Extra: typing
Requires-Dist: mypy ; extra == 'typing'
